.installed.cfg
CHANGES.rst
MANIFEST.in
README.rst
buildout.cfg
setup.py
bobtemplates/__init__.py
bobtemplates/hooks.py
bobtemplates.affinitic.egg-info/PKG-INFO
bobtemplates.affinitic.egg-info/SOURCES.txt
bobtemplates.affinitic.egg-info/dependency_links.txt
bobtemplates.affinitic.egg-info/namespace_packages.txt
bobtemplates.affinitic.egg-info/not-zip-safe
bobtemplates.affinitic.egg-info/requires.txt
bobtemplates.affinitic.egg-info/top_level.txt
bobtemplates/affinitic/__init__.py
bobtemplates/affinitic/basic_plone_buildout/.gitignore
bobtemplates/affinitic/basic_plone_buildout/.mrbob.ini
bobtemplates/affinitic/basic_plone_buildout/README.rst.bob
bobtemplates/affinitic/basic_plone_buildout/bootstrap.py
bobtemplates/affinitic/basic_plone_buildout/buildout.cfg.bob
bobtemplates/affinitic/basic_plone_buildout/docs/HISTORY.txt
bobtemplates/affinitic/basic_plone_buildout/docs/LICENSE.GPL
bobtemplates/affinitic/diazo_theme/.gitignore
bobtemplates/affinitic/diazo_theme/.mrbob.ini
bobtemplates/affinitic/diazo_theme/README.rst.bob
bobtemplates/affinitic/diazo_theme/setup.py.bob
bobtemplates/affinitic/diazo_theme/docs/HISTORY.txt
bobtemplates/affinitic/diazo_theme/docs/LICENSE.GPL
bobtemplates/affinitic/diazo_theme/src/.DS_Store
bobtemplates/affinitic/diazo_theme/src/+package.namespace+/__init__.py
bobtemplates/affinitic/diazo_theme/src/+package.namespace+/+package.name+/.DS_Store
bobtemplates/affinitic/diazo_theme/src/+package.namespace+/+package.name+/__init__.py
bobtemplates/affinitic/diazo_theme/src/+package.namespace+/+package.name+/configure.zcml.bob
bobtemplates/affinitic/diazo_theme/src/+package.namespace+/+package.name+/interfaces.py
bobtemplates/affinitic/diazo_theme/src/+package.namespace+/+package.name+/profiles.zcml.bob
bobtemplates/affinitic/diazo_theme/src/+package.namespace+/+package.name+/profiles/.DS_Store
bobtemplates/affinitic/diazo_theme/src/+package.namespace+/+package.name+/profiles/default/browserlayer.xml.bob
bobtemplates/affinitic/diazo_theme/src/+package.namespace+/+package.name+/profiles/default/cssregistry.xml.bob
bobtemplates/affinitic/diazo_theme/src/+package.namespace+/+package.name+/profiles/default/metadata.xml.bob
bobtemplates/affinitic/diazo_theme/src/+package.namespace+/+package.name+/profiles/default/theme.xml.bob
