Metadata-Version: 1.1
Name: bobtemplates.affinitic
Version: 1.0
Summary: Templates for Affinitic Plone projects.
Home-page: https://github.com/affinitic/bobtemplates.affinitic
Author: Affinitic
Author-email: info@affinitic.be
License: GPL version 2
Keywords: web plone zope skeleton project
Platform: UNKNOWN
Classifier: Environment :: Console
Classifier: Intended Audience :: Developers
Classifier: Natural Language :: English
Classifier: Operating System :: OS Independent
Classifier: Programming Language :: Python
Classifier: Development Status :: 5 - Production/Stable
Classifier: Topic :: Software Development :: Code Generators
Classifier: Topic :: Utilities
Classifier: License :: OSI Approved :: GNU General Public License v2 (GPLv2)
